compbaseball/__init__.py
compbaseball/baseball.py
compbaseball/build_data.py
compbaseball/inputs.json
compbaseball/playerchoices.json
compbaseball/utils.py
compbaseball/tests/__init__.py
compbaseball/tests/test.py
matchups/__init__.py
matchups/defaults.json
matchups/inputs.json
matchups/matchups.py
matchups/playerchoices.json
matchups/schema.json
matchups/statcast.parquet
matchups/statcast2018.parquet
matchups/utils.py
matchups/tests/__init__.py
matchups/tests/test.py
matchups/tests/test_inputs.py
matchups/tests/test_outputs.py
matchups-0.4.0.dist-info/LICENSE
matchups-0.4.0.dist-info/METADATA
matchups-0.4.0.dist-info/WHEEL
matchups-0.4.0.dist-info/top_level.txt
matchups-0.4.0.dist-info/RECORD
